telegram_pot/__init__.py
telegram_pot/apis.py
telegram_pot/bot.py
telegram_pot/exceptions.py
telegram_pot/model.py
telegram_pot/models.py
telegram_pot-0.0.8.dist-info/LICENSE
telegram_pot-0.0.8.dist-info/METADATA
telegram_pot-0.0.8.dist-info/WHEEL
telegram_pot-0.0.8.dist-info/top_level.txt
telegram_pot-0.0.8.dist-info/RECORD
