Metadata-Version: 2.1
Name: telegram-pot
Version: 0.0.8
Summary: A Telegram python bot api
Author-email: Amin Fazlali <amin@fazlali.net>
Project-URL: Homepage, https://github.com/fazlali/telegram_pot
Project-URL: Bug Tracker, https://github.com/fazlali/telegram_pot/issues
Classifier: Programming Language :: Python :: 3
Classifier: License :: OSI Approved :: MIT License
Classifier: Operating System :: OS Independent
Requires-Python: >=3.7
License-File: LICENSE
